testpypiEG/__init__.py
testpypiEG/m_mod_EG.py
testpypiEG-0.0.1.dist-info/LICENSE.txt
testpypiEG-0.0.1.dist-info/METADATA
testpypiEG-0.0.1.dist-info/WHEEL
testpypiEG-0.0.1.dist-info/top_level.txt
testpypiEG-0.0.1.dist-info/RECORD
