Metadata-Version: 2.1
Name: testpypiEG
Version: 0.0.1
Summary: My test package
Author-email: EG <elizaganca@gmail.com>
License: MIT License
Keywords: testpypiEG,name,surname
Classifier: Framework :: Ansible
Classifier: Environment :: Plugins
Requires-Python: >=3.0
License-File: LICENSE.txt
Requires-Dist: numpy
